setup.cfg
setup.py
biofloat/ArgoData.py
biofloat/__init__.py
biofloat/calibrate.py
biofloat/converters.py
biofloat/exceptions.py
biofloat/utils.py
biofloat.egg-info/PKG-INFO
biofloat.egg-info/SOURCES.txt
biofloat.egg-info/dependency_links.txt
biofloat.egg-info/requires.txt
biofloat.egg-info/top_level.txt
scripts/__init__.py
scripts/load_biofloat_cache.py
scripts/woa_calibration.py