Metadata-Version: 1.1
Name: biofloat
Version: 0.4.4
Summary: Software for working with data from Bio-Argo floats
Home-page: https://github.com/biofloat/biofloat
Author: Mike McCann
Author-email: mccann@mbari.org
License: MIT
Keywords: Oceanography Argo Bio-Argo drifting buoys floats
Platform: UNKNOWN
Requires: Python (>=2.7)
